ae_qem/__init__.py
ae_qem/mitigation.py
ae_qem/models.py
ae_qem/plot_utils.py
ae_qem/utils.py
ae_qem/data/chkpoints/A.h5
ae_qem/data/chkpoints/B.h5
ae_qem/data/chkpoints/C.h5
ae_qem/data/chkpoints/D.h5
ae_qem/data/chkpoints/E.h5
ae_qem/data/chkpoints/F.h5
ae_qem/data/models/4qubit_1D_origin_softmax_Keras2.keras
ae_qem/data/models/4qubit_1D_origin_softmax_Keras3.keras
ae_qem-0.1.0.dist-info/licenses/LICENSE
ae_qem-0.1.0.dist-info/METADATA
ae_qem-0.1.0.dist-info/WHEEL
ae_qem-0.1.0.dist-info/top_level.txt
ae_qem-0.1.0.dist-info/RECORD
