Metadata-Version: 2.4
Name: ae-qem
Version: 0.1.0
Summary: Autoencoder-based error mitigation and visualization
Author-email: LIN XIAO DAO <112755009@g.nccu.edu.tw>
License: MIT License
Project-URL: Homepage, https://github.com/Y-Frieren-Y/ae-qem
Project-URL: Issues, https://github.com/Y-Frieren-Y/ae-qem/issues
Classifier: Programming Language :: Python :: 3
Classifier: License :: OSI Approved :: MIT License
Classifier: Operating System :: OS Independent
Requires-Python: >=3.9
License-File: LICENSE
Requires-Dist: numpy
Requires-Dist: qiskit<2.0,>=1.2
Requires-Dist: qiskit-ibm-runtime>0.3
Requires-Dist: qiskit-aer
Requires-Dist: matplotlib
Requires-Dist: pylatexenc
Requires-Dist: tensorflow<3.0,>2.0
Requires-Dist: dash
Requires-Dist: plotly
Dynamic: license-file
